{"resourceType":"CodeSystem","id":"action-participant-function","meta":{"lastUpdated":"2023-03-26T15:21:02.749+11:00","profile":["http://hl7.org/fhir/StructureDefinition/shareablecodesystem"]},"text":{"status":"generated","div":"<div xmlns=\"http://www.w3.org/1999/xhtml\">\n            <p>This code system \n              <code>http://hl7.org/fhir/action-participant-function</code> defines the following codes:\n            </p>\n            <table class=\"codes\">\n              <tr>\n                <td style=\"white-space:nowrap\">\n                  <b>Code</b>\n                </td>\n                <td>\n                  <b>Display</b>\n                </td>\n                <td>\n                  <b>Definition</b>\n                </td>\n              </tr>\n              <tr>\n                <td style=\"white-space:nowrap\">performer\n                  <a name=\"action-participant-function-performer\"> </a>\n                </td>\n                <td>Performer</td>\n                <td>The participant is the performer of the action.</td>\n              </tr>\n              <tr>\n                <td style=\"white-space:nowrap\">author\n                  <a name=\"action-participant-function-author\"> </a>\n                </td>\n                <td>Author</td>\n                <td>The participant is the author of the result of the action.</td>\n              </tr>\n              <tr>\n                <td style=\"white-space:nowrap\">reviewer\n                  <a name=\"action-participant-function-reviewer\"> </a>\n                </td>\n                <td>Reviewer</td>\n                <td>The participant is reviewing the result of the action.</td>\n              </tr>\n              <tr>\n                <td style=\"white-space:nowrap\">witness\n                  <a name=\"action-participant-function-witness\"> </a>\n                </td>\n                <td>Witness</td>\n                <td>The participant is a witness to the action being performed.</td>\n              </tr>\n            </table>\n          </div>"},"extension":[{"url":"http://hl7.org/fhir/StructureDefinition/structuredefinition-wg","valueCode":"cds"},{"url":"http://hl7.org/fhir/StructureDefinition/structuredefinition-standards-status","valueCode":"trial-use"},{"url":"http://hl7.org/fhir/StructureDefinition/structuredefinition-fmm","valueInteger":3}],"url":"http://hl7.org/fhir/action-participant-function","identifier":[{"system":"urn:ietf:rfc:3986","value":"urn:oid:2.16.840.1.113883.4.642.4.1946"}],"version":"5.0.0","name":"ActionParticipantFunction","title":"Action Participant Function","status":"active","experimental":false,"date":"2021-01-05T10:01:24+11:00","publisher":"HL7 (FHIR Project)","contact":[{"telecom":[{"system":"url","value":"http://hl7.org/fhir"},{"system":"email","value":"fhir@lists.hl7.org"}]}],"description":"The function performed by the participant for the action.","jurisdiction":[{"coding":[{"system":"http://unstats.un.org/unsd/methods/m49/m49.htm","code":"001","display":"World"}]}],"caseSensitive":true,"valueSet":"http://hl7.org/fhir/ValueSet/action-participant-function","content":"complete","concept":[{"code":"performer","display":"Performer","definition":"The participant is the performer of the action."},{"code":"author","display":"Author","definition":"The participant is the author of the result of the action."},{"code":"reviewer","display":"Reviewer","definition":"The participant is reviewing the result of the action."},{"code":"witness","display":"Witness","definition":"The participant is a witness to the action being performed."}]}